{
  "$type": "Octopus.Core.Model.ServerTasks.ServerTask, Octopus.Core",
  "Id": "ServerTasks-957",
  "Name": "Deploy",
  "Arguments": {
    "DeploymentId": "Deployments-142"
  },
  "Description": "Deploy DeploymentTests_Project1 release 0.0.10 to Prod",
  "QueueTime": "2017-03-13T22:19:44.4304902-03:00",
  "QueueTimeExpiry": "10675199.02:48:05.4775807",
  "ExecutionTimeExpiry": "00:00:00",
  "StartTime": "2017-03-13T22:19:44.4744856-03:00",
  "LastUpdatedTime": "2017-03-13T22:19:49.6830762-03:00",
  "CompletedTime": "2017-03-13T22:19:49.6830762-03:00",
  "ErrorMessage": "",
  "ConcurrencyTag": "/Projects-3/Environments-2",
  "State": "Success",
  "HasPendingInterruptions": false,
  "HasWarningsOrErrors": false,
  "ServerVersion": "3.8.4+Branch.master.Sha.1b250ca4d7c1d42aa029771ed15851e6ed11ff83",
  "ServerNode": "DEVBOX",
  "LogDifferentiationToken": "9QHMKEPGDU",
  "AdditionalDescription": null,
  "DurationSeconds": 5,
  "ProjectId": "Projects-23",
  "EnvironmentId": "Environments-22",
  "TenantId": null,
  "ExtendedViewLogPermissions": [],
  "ExtendedCreatePermissions": [
    "DeploymentCreate"
  ],
  "CanRerun": false,
  "Properties": {}
}