{
  "$type": "Octopus.Core.Model.Events.Event, Octopus.Core",
  "Id": "Events-6646",
  "RelatedDocumentIds": [
    "Environments-23"
  ],
  "ProjectId": null,
  "EnvironmentId": "Environments-23",
  "TenantId": null,
  "Category": "DeploymentQueued",
  "UserId": "Users-1",
  "Username": "admin",
  "Occurred": "2017-01-30T22:59:13.7963329-03:00",
  "Message": "Deployed DashboardTests_Project2 release 0.0.1 to Stage",
  "MessageReferences": [
    {
      "ReferencedDocumentId": "NotFound",
      "StartIndex": 9,
      "Length": 23
    },
    {
      "ReferencedDocumentId": "NotFound",
      "StartIndex": 41,
      "Length": 5
    },
    {
      "ReferencedDocumentId": "Environments-23",
      "StartIndex": 50,
      "Length": 5
    }
  ],
  "Comments": null,
  "Details": null,
  "IdentityEstablishedWith": "Session cookie"
}