{
  "$type": "Octopus.Core.Model.Events.Event, Octopus.Core",
  "Id": "Events-7137",
  "RelatedDocumentIds": [
    "Environments-62"
  ],
  "ProjectId": null,
  "EnvironmentId": "Environments-62",
  "TenantId": null,
  "Category": "Created",
  "UserId": "Users-1",
  "Username": "admin",
  "Occurred": "2017-07-07T04:04:49.9476014+00:00",
  "Message": "Environment IWEBOLIMWMNR7JP was created",
  "MessageReferences": [
    {
      "ReferencedDocumentId": "Environments-62",
      "StartIndex": 12,
      "Length": 15
    }
  ],
  "Comments": null,
  "Details": "<span>{\r&para;<br>  \"Id\": \"Environments-62\",\r&para;<br>  \"Name\": \"IWEBOLIMWMNR7JP\",\r&para;<br>  \"Description\": \"\",\r&para;<br>  \"SortOrder\": 4,\r&para;<br>  \"UseGuidedFailure\": false\r&para;<br>}</span>",
  "IdentityEstablishedWith": "API key 'Octoposh Automated Testing' created Sun, 04 Dec 2016 03:19:06 GMT"
}