{
  "$type": "Octopus.Core.Model.Projects.Deployment, Octopus.Core",
  "Id": "Deployments-127",
  "Name": "Deploy to Prod",
  "Created": "2017-02-06T06:26:03.889515+00:00",
  "ForcePackageDownload": false,
  "ForcePackageRedeployment": false,
  "Comments": null,
  "SkipActions": [],
  "SpecificMachineIds": [],
  "ExcludedMachineIds": [],
  "UseGuidedFailure": false,
  "TentacleRetentionPeriod": {
    "Unit": "Items",
    "QuantityToKeep": 0,
    "ShouldKeepForever": true
  },
  "EnvironmentId": "Environments-2",
  "TenantId": null,
  "TaskId": "ServerTasks-235",
  "ReleaseId": "Releases-103",
  "ProjectId": "Projects-22",
  "ChannelId": "Channels-23",
  "DeploymentProcessId": "deploymentprocess-Projects-22-s-5-F2PDG",
  "ManifestVariableSetId": null,
  "ProjectGroupId": "ProjectGroups-42",
  "DeployedBy": "admin",
  "StateObject": null
}