{
  "$type": "Octopus.Core.Model.Events.Event, Octopus.Core",
  "Id": "Events-2460",
  "RelatedDocumentIds": [
    "Deployments-78",
    "Projects-4",
    "Releases-59",
    "Environments-1"
  ],
  "ProjectId": "Projects-4",
  "EnvironmentId": "Environments-1",
  "TenantId": null,
  "Category": "DeploymentSucceeded",
  "UserId": "users-system",
  "Username": "system",
  "Occurred": "2017-03-07T00:52:48.5689279+00:00",
  "Message": "Deploy to Dev succeeded  for DeploymentTests_Project2 release 0.0.5 to Dev",
  "MessageReferences": [
    {
      "ReferencedDocumentId": "Deployments-78",
      "StartIndex": 0,
      "Length": 13
    },
    {
      "ReferencedDocumentId": "Projects-4",
      "StartIndex": 29,
      "Length": 24
    },
    {
      "ReferencedDocumentId": "Releases-59",
      "StartIndex": 62,
      "Length": 5
    },
    {
      "ReferencedDocumentId": "Environments-1",
      "StartIndex": 71,
      "Length": 3
    }
  ],
  "Comments": null,
  "Details": null,
  "IdentityEstablishedWith": "Unknown"
}