{
  "$type": "Octopus.Core.Model.Events.Event, Octopus.Core",
  "Id": "Events-1553",
  "RelatedDocumentIds": [
    "Projects-5",
    "Environments-2"
  ],
  "ProjectId": "Projects-5",
  "EnvironmentId": "Environments-2",
  "TenantId": null,
  "Category": "DeploymentSucceeded",
  "UserId": "users-system",
  "Username": "system",
  "Occurred": "2017-02-11T01:07:17.5124186-03:00",
  "Message": "Deploy to Prod (#2) succeeded  for TestProject1 release 0.0.32 to Prod",
  "MessageReferences": [
    {
      "ReferencedDocumentId": "NotFound",
      "StartIndex": 0,
      "Length": 19
    },
    {
      "ReferencedDocumentId": "Projects-5",
      "StartIndex": 35,
      "Length": 12
    },
    {
      "ReferencedDocumentId": "NotFound",
      "StartIndex": 56,
      "Length": 6
    },
    {
      "ReferencedDocumentId": "Environments-2",
      "StartIndex": 66,
      "Length": 4
    }
  ],
  "Comments": null,
  "Details": null,
  "IdentityEstablishedWith": "Unknown"
}