{
  "$type": "Octopus.Core.Model.Events.Event, Octopus.Core",
  "Id": "Events-1097",
  "RelatedDocumentIds": [],
  "ProjectId": null,
  "EnvironmentId": null,
  "TenantId": null,
  "Category": "MachineAdded",
  "UserId": "Users-1",
  "Username": "admin",
  "Occurred": "2017-02-04T19:43:30.7825388-03:00",
  "Message": "Machine ListeningTentacle3 was created (domain-event)",
  "MessageReferences": [
    {
      "ReferencedDocumentId": "NotFound",
      "StartIndex": 8,
      "Length": 18
    }
  ],
  "Comments": null,
  "Details": null,
  "IdentityEstablishedWith": "Session cookie"
}