{
  "$type": "Octopus.Core.Model.Events.Event, Octopus.Core",
  "Id": "Events-947",
  "RelatedDocumentIds": [
    "ServerTasks-156"
  ],
  "ProjectId": null,
  "EnvironmentId": null,
  "TenantId": null,
  "Category": "TaskCanceled",
  "UserId": "Users-1",
  "Username": "admin",
  "Occurred": "2017-01-30T23:46:26.3083385-03:00",
  "Message": "Task Deploy DashboardTests_Project2 release 0.0.1 to Stage #76 was canceled",
  "MessageReferences": [
    {
      "ReferencedDocumentId": "ServerTasks-156",
      "StartIndex": 5,
      "Length": 57
    }
  ],
  "Comments": null,
  "Details": null,
  "IdentityEstablishedWith": "Session cookie"
}