{
  "$type": "Octopus.Core.Model.Events.Event, Octopus.Core",
  "Id": "Events-35",
  "RelatedDocumentIds": [
    "Deployments-77",
    "Projects-4",
    "Environments-2"
  ],
  "ProjectId": "Projects-4",
  "EnvironmentId": "Environments-2",
  "TenantId": null,
  "Category": "DeploymentSucceeded",
  "UserId": "users-system",
  "Username": "system",
  "Occurred": "2017-02-06T03:11:05.0414211-03:00",
  "Message": "Deploy to Prod succeeded  for DeploymentTests_Project2 release 0.0.3 to Prod",
  "MessageReferences": [
    {
      "ReferencedDocumentId": "Deployments-77",
      "StartIndex": 0,
      "Length": 14
    },
    {
      "ReferencedDocumentId": "Projects-4",
      "StartIndex": 30,
      "Length": 24
    },
    {
      "ReferencedDocumentId": "NotFound",
      "StartIndex": 63,
      "Length": 5
    },
    {
      "ReferencedDocumentId": "Environments-2",
      "StartIndex": 72,
      "Length": 4
    }
  ],
  "Comments": null,
  "Details": null,
  "IdentityEstablishedWith": "Unknown"
}