{
  "$type": "Octopus.Core.Model.Events.Event, Octopus.Core",
  "Id": "Events-1323",
  "RelatedDocumentIds": [
    "Projects-5",
    "Environments-1"
  ],
  "ProjectId": "Projects-5",
  "EnvironmentId": "Environments-1",
  "TenantId": null,
  "Category": "DeploymentStarted",
  "UserId": "users-system",
  "Username": "system",
  "Occurred": "2017-03-06T20:45:33.1009198-03:00",
  "Message": "Deploy to Dev (#2) started  for TestProject1 release 0.0.32 to Dev",
  "MessageReferences": [
    {
      "ReferencedDocumentId": "NotFound",
      "StartIndex": 0,
      "Length": 18
    },
    {
      "ReferencedDocumentId": "Projects-5",
      "StartIndex": 32,
      "Length": 12
    },
    {
      "ReferencedDocumentId": "NotFound",
      "StartIndex": 53,
      "Length": 6
    },
    {
      "ReferencedDocumentId": "Environments-1",
      "StartIndex": 63,
      "Length": 3
    }
  ],
  "Comments": null,
  "Details": null,
  "IdentityEstablishedWith": "Unknown"
}