{
  "$type": "Octopus.Core.Model.Projects.Deployment, Octopus.Core",
  "Id": "Deployments-123",
  "Name": "Deploy to Dev",
  "Created": "2017-03-07T04:43:09.5104337+00:00",
  "ForcePackageDownload": false,
  "ForcePackageRedeployment": false,
  "Comments": null,
  "SkipActions": [],
  "SpecificMachineIds": [],
  "ExcludedMachineIds": [],
  "UseGuidedFailure": false,
  "TentacleRetentionPeriod": {
    "Unit": "Items",
    "QuantityToKeep": 0,
    "ShouldKeepForever": true
  },
  "EnvironmentId": "Environments-1",
  "TenantId": null,
  "TaskId": "ServerTasks-455",
  "ReleaseId": "Releases-74",
  "ProjectId": "Projects-4",
  "ChannelId": "Channels-4",
  "DeploymentProcessId": "deploymentprocess-Projects-4-s-0-DN849",
  "ManifestVariableSetId": "variableset-Deployments-123",
  "ProjectGroupId": "ProjectGroups-22",
  "DeployedBy": "admin",
  "StateObject": null
}